ansys/seascape/__init__.py
ansys/seascape/redhawk.py
ansys/seascape/scapp.py
ansys/seascape/utils.py
ansys_seascape-0.2.0.dist-info/LICENSE
ansys_seascape-0.2.0.dist-info/WHEEL
ansys_seascape-0.2.0.dist-info/METADATA
ansys_seascape-0.2.0.dist-info/RECORD
