Metadata-Version: 2.1
Name: ansys-seascape
Version: 0.2.0
Summary: A pythonic remotable interface to RedHawkSC and TotemSC
Author-email: "ANSYS, Inc." <pyansys.support@ansys.com>
Maintainer-email: Abhishek Kale <abhishek.kale@ansys.com>
Requires-Python: >=3.7,<4
Classifier: Development Status :: 4 - Beta
Classifier: Intended Audience :: Science/Research
Classifier: Topic :: Scientific/Engineering :: Information Analysis
Classifier: License :: OSI Approved :: MIT License
Classifier: Operating System :: OS Independent
Classifier: Programming Language :: Python :: 3.7
Classifier: Programming Language :: Python :: 3.8
Classifier: Programming Language :: Python :: 3.9
Classifier: Programming Language :: Python :: 3.10
Requires-Dist: importlib-metadata>=4.0,<5; python_version<='3.8'
Requires-Dist: requests>=2.23
Requires-Dist: ansys-sphinx-theme==0.7.2 ; extra == "doc"
Requires-Dist: numpydoc==1.5.0 ; extra == "doc"
Requires-Dist: Sphinx==5.3.0 ; extra == "doc"
Requires-Dist: sphinx-copybutton==0.5.1 ; extra == "doc"
Requires-Dist: pytest==7.2.0 ; extra == "tests"
Requires-Dist: pytest-cov==4.0.0 ; extra == "tests"
Project-URL: Documentation, https://seascape.docs.pyansys.com
Project-URL: Source, https://github.com/pyansys/pyseascape
Provides-Extra: doc
Provides-Extra: tests
